afcpy/__init__.py
afcpy/analysis.py
afcpy/models.py
afcpy/results.py
afcpy/data/jacki/gad2/tb_abw25_170409a_clean.mat
afcpy/data/jacki/gad2/tb_abw25_170411a_clean.mat
afcpy/data/jacki/gad2/tb_abw25_170417a_clean.mat
afcpy/data/jacki/gad2/tb_abw25_170430a_clean.mat
afcpy/data/jacki/gad2/tb_abw25_170502a_clean.mat
afcpy/data/jacki/gad2/tb_abw25_170504a_clean.mat
afcpy/data/jacki/gad2/tb_abw25_170507a_clean.mat
afcpy/data/jacki/gad2/tb_abw25_170509a_clean.mat
afcpy/data/jacki/gad2/tb_abw25_170512a_clean.mat
afcpy/data/jacki/gad2/tb_abw25_170516a_clean.mat
afcpy/data/jacki/gad2/tb_abw25_170518a_clean.mat
afcpy/data/jacki/gad2/tb_abw25_170522a_clean.mat
afcpy/data/jacki/gad2/tb_abw35_170831a_clean.mat
afcpy/data/jacki/gad2/tb_abw35_170905a_clean.mat
afcpy/data/jacki/gad2/tb_abw35_170908a_clean.mat
afcpy/data/jacki/gad2/tb_abw35_170910a_clean.mat
afcpy/data/jacki/gad2/tb_abw35_170914a_clean.mat
afcpy/data/jacki/gad2/tb_abw35_170918a_contra_clean.mat
afcpy/data/jacki/gad2/tb_abw35_170919a_clean.mat
afcpy/data/jacki/gad2/tb_abw35_170920a_contra_clean.mat
afcpy/data/jacki/gad2/tb_abw35_170922a_clean.mat
afcpy/data/jacki/gad2/tb_abw35_170925a_clean.mat
afcpy/data/jacki/gad2/tb_abw35_170927a_clean.mat
afcpy/data/jacki/gad2/tb_abw35_171004a_clean.mat
afcpy/data/jacki/gad2/tb_abw35_171005a_contra_clean.mat
afcpy/data/jacki/gad2/tb_abw36_171026a_clean.mat
afcpy/data/jacki/gad2/tb_abw36_171028a_clean.mat
afcpy/data/jacki/gad2/tb_abw36_171031a_clean.mat
afcpy/data/jacki/gad2/tb_abw36_171102a_contra_clean.mat
afcpy/data/jacki/gad2/tb_abw36_171122a_clean.mat
afcpy/data/jacki/gad2/tb_abw36_171124a_clean.mat
afcpy/data/jacki/gad2/tb_abw36_171126a_clean.mat
afcpy/data/jacki/gad2/tb_abw36_171127a_clean.mat
afcpy/data/jacki/gad2/tb_abw42_180111a_clean.mat
afcpy/data/jacki/gad2/tb_abw42_180116a_clean.mat
afcpy/data/jacki/gad2/tb_abw42_180119a_clean.mat
afcpy/data/jacki/gad2/tb_abw42_180127a_clean.mat
afcpy/data/jacki/gad2/tb_abw42_180131a_clean.mat
afcpy-1.0.2.dist-info/LICENSE
afcpy-1.0.2.dist-info/METADATA
afcpy-1.0.2.dist-info/WHEEL
afcpy-1.0.2.dist-info/top_level.txt
afcpy-1.0.2.dist-info/RECORD
