Metadata-Version: 2.1
Name: afcpy
Version: 1.0.2
Summary: UNKNOWN
Home-page: https://github.com/jbhunt/afcpy
Author: Josh Hunt
Author-email: hunt.brian.joshua@gmail.com
License: UNKNOWN
Platform: UNKNOWN
Classifier: Programming Language :: Python :: 3
Classifier: License :: OSI Approved :: MIT License
Classifier: Operating System :: OS Independent
Requires-Dist: numpy
Requires-Dist: scipy
Requires-Dist: sklearn
Requires-Dist: statsmodels
Requires-Dist: pandas
Requires-Dist: xlrd
